zstandard/__init__.py
zstandard/__init__.pyi
zstandard/_cffi.cpython-313-s390x-linux-musl.so
zstandard/backend_c.cpython-313-s390x-linux-musl.so
zstandard/backend_cffi.py
zstandard/py.typed
zstandard-0.24.0.dist-info/METADATA
zstandard-0.24.0.dist-info/WHEEL
zstandard-0.24.0.dist-info/top_level.txt
zstandard-0.24.0.dist-info/RECORD
zstandard-0.24.0.dist-info/licenses/LICENSE
