Metadata-Version: 2.1
Name: zstandard
Version: 0.24.0
Summary: Zstandard bindings for Python
Author-email: Gregory Szorc <gregory.szorc@gmail.com>
License: BSD
Project-URL: Homepage, https://github.com/indygreg/python-zstandard
Project-URL: Documentation, https://python-zstandard.readthedocs.io/en/latest/
Keywords: zstandard,zstd,compression
Classifier: Development Status :: 5 - Production/Stable
Classifier: Intended Audience :: Developers
Classifier: License :: OSI Approved :: BSD License
Classifier: Programming Language :: C
Classifier: Programming Language :: Python :: 3.9
Classifier: Programming Language :: Python :: 3.10
Classifier: Programming Language :: Python :: 3.11
Classifier: Programming Language :: Python :: 3.12
Classifier: Programming Language :: Python :: 3.13
Classifier: Programming Language :: Python :: 3.14
Requires-Python: >=3.9
Provides-Extra: cffi
Requires-Dist: cffi>=1.17; (python_version >= "3.13" and platform_python_implementation != "PyPy") and extra == "cffi"
